brythonmagic.py
brythonmagic-0.2.1.dist-info/DESCRIPTION.rst
brythonmagic-0.2.1.dist-info/METADATA
brythonmagic-0.2.1.dist-info/RECORD
brythonmagic-0.2.1.dist-info/WHEEL
brythonmagic-0.2.1.dist-info/metadata.json
brythonmagic-0.2.1.dist-info/top_level.txt
