Metadata-Version: 2.0
Name: brythonmagic
Version: 0.2.1
Summary: Magics to use brython in Jupyter notebook.
Home-page: https://github.com/kikocorreoso/brythonmagic
Author: Kikocorreoso
Author-email: UNKNOWN
License: MIT
Keywords: brython ipython jupyter notebook javascript
Platform: UNKNOWN
Classifier: Topic :: Text Processing :: Markup :: HTML
Classifier: License :: OSI Approved :: MIT License
Classifier: Programming Language :: Python :: 2
Classifier: Programming Language :: Python :: 2.7
Classifier: Programming Language :: Python :: 3
Classifier: Programming Language :: Python :: 3.3
Classifier: Programming Language :: Python :: 3.4
Classifier: Programming Language :: Python :: 3.5
